LICENSE
MANIFEST.in
README.rst
setup.py
notario/__init__.py
notario/_compat.py
notario/decorators.py
notario/engine.py
notario/exceptions.py
notario/normal.py
notario/regex.py
notario/store.py
notario/utils.py
notario.egg-info/PKG-INFO
notario.egg-info/SOURCES.txt
notario.egg-info/dependency_links.txt
notario.egg-info/not-zip-safe
notario.egg-info/top_level.txt
notario/tests/__init__.py
notario/tests/test_decorators.py
notario/tests/test_engine.py
notario/tests/test_exceptions.py
notario/tests/test_functional.py
notario/tests/test_normal.py
notario/tests/test_regex.py
notario/tests/test_utils.py
notario/tests/util.py
notario/tests/validators/__init__.py
notario/tests/validators/test_chainable.py
notario/tests/validators/test_cherry.py
notario/tests/validators/test_hybrid.py
notario/tests/validators/test_iterables.py
notario/tests/validators/test_recursive.py
notario/tests/validators/test_types.py
notario/validators/__init__.py
notario/validators/__init__.pyc
notario/validators/chainable.py
notario/validators/iterables.py
notario/validators/recursive.py
notario/validators/types.py